[{"id":"Albanía","name":"Albanía"},{"id":"American Samoa","name":"American Samoa"},{"id":"Andorra","name":"Andorra"},{"id":"Angóla","name":"Angóla"},{"id":"Anguilla","name":"Anguilla"},{"id":"Antigua","name":"Antigua"},{"id":"Argentína","name":"Argentína"},{"id":"Armenía","name":"Armenía"},{"id":"Aruba","name":"Aruba"},{"id":"Austurríki","name":"Austurríki"},{"id":"Azerbaijan","name":"Azerbaijan"},{"id":"Ástralía","name":"Ástralía"},{"id":"Bahamaeyjar","name":"Bahamaeyjar"},{"id":"Bahrein","name":"Bahrein"},{"id":"Bandaríkin - annað","name":"Bandaríkin - annað"},{"id":"Bandaríkin - Flórída","name":"Bandaríkin - Flórída"},{"id":"Bandaríkin - Kalifornía","name":"Bandaríkin - Kalifornía"},{"id":"Bandaríkin - Las Vegas","name":"Bandaríkin - Las Vegas"},{"id":"Bandaríkin - New York","name":"Bandaríkin - New York"},{"id":"Barbados","name":"Barbados"},{"id":"Belgía","name":"Belgía"},{"id":"Belís","name":"Belís"},{"id":"Bonaire","name":"Bonaire"},{"id":"Bosnía","name":"Bosnía"},{"id":"Botswana","name":"Botswana"},{"id":"Bólivía","name":"Bólivía"},{"id":"Brasílía","name":"Brasílía"},{"id":"Bresku Jómfrúaeyjar","name":"Bresku Jómfrúaeyjar"},{"id":"Bretland","name":"Bretland"},{"id":"Brúnei","name":"Brúnei"},{"id":"Búlgaría","name":"Búlgaría"},{"id":"Caymaneyjar","name":"Caymaneyjar"},{"id":"Curacao","name":"Curacao"},{"id":"Danmörk","name":"Danmörk"},{"id":"Dominica","name":"Dominica"},{"id":"Dóminikanska lýðveldið","name":"Dóminikanska lýðveldið"},{"id":"Egyptaland","name":"Egyptaland"},{"id":"Eistland","name":"Eistland"},{"id":"Ekvador","name":"Ekvador"},{"id":"El Salvador","name":"El Salvador"},{"id":"Fijieyjar","name":"Fijieyjar"},{"id":"Filipseyjar","name":"Filipseyjar"},{"id":"Finnland","name":"Finnland"},{"id":"Frakkland - meginland","name":"Frakkland - meginland"},{"id":"Franska Gíena","name":"Franska Gíena"},{"id":"Franska Korsíka","name":"Franska Korsíka"},{"id":"Franska Pólynesía","name":"Franska Pólynesía"},{"id":"Gana","name":"Gana"},{"id":"Georgía","name":"Georgía"},{"id":"Gíbraltar","name":"Gíbraltar"},{"id":"Grikkland","name":"Grikkland"},{"id":"Guam","name":"Guam"},{"id":"Guernsey","name":"Guernsey"},{"id":"Gvadelúp","name":"Gvadelúp"},{"id":"Gvatemala","name":"Gvatemala"},{"id":"Holland","name":"Holland"},{"id":"Hondúras","name":"Hondúras"},{"id":"Hong Kong","name":"Hong Kong"},{"id":"Hvíta Rússland","name":"Hvíta Rússland"},{"id":"Indland","name":"Indland"},{"id":"Indónesía","name":"Indónesía"},{"id":"Írak","name":"Írak"},{"id":"Írland","name":"Írland"},{"id":"Ísland","name":"Ísland"},{"id":"Ísrael","name":"Ísrael"},{"id":"Ítalía","name":"Ítalía"},{"id":"Ítalía - Sardinía","name":"Ítalía - Sardinía"},{"id":"Ítalía - Sikiley","name":"Ítalía - Sikiley"},{"id":"Jamaíka","name":"Jamaíka"},{"id":"Japan","name":"Japan"},{"id":"Jersey","name":"Jersey"},{"id":"Jórdanía","name":"Jórdanía"},{"id":"Kamerún","name":"Kamerún"},{"id":"Kanada","name":"Kanada"},{"id":"Katar","name":"Katar"},{"id":"Kazakhstan","name":"Kazakhstan"},{"id":"Kenía","name":"Kenía"},{"id":"Kína","name":"Kína"},{"id":"Kosovo","name":"Kosovo"},{"id":"Kosta Ríka","name":"Kosta Ríka"},{"id":"Kólumbía","name":"Kólumbía"},{"id":"Kórea","name":"Kórea"},{"id":"Króatía","name":"Króatía"},{"id":"Kúveit","name":"Kúveit"},{"id":"Kýpur","name":"Kýpur"},{"id":"Laos","name":"Laos"},{"id":"Lesótó","name":"Lesótó"},{"id":"Lettland","name":"Lettland"},{"id":"Litháen","name":"Litháen"},{"id":"Líbanon","name":"Líbanon"},{"id":"Lúxemborg","name":"Lúxemborg"},{"id":"Madeira","name":"Madeira"},{"id":"Makedónía","name":"Makedónía"},{"id":"Malasía","name":"Malasía"},{"id":"Malta","name":"Malta"},{"id":"Marokkó","name":"Marokkó"},{"id":"Martinique","name":"Martinique"},{"id":"Mayotte","name":"Mayotte"},{"id":"Máritanía","name":"Máritanía"},{"id":"Mexíkó","name":"Mexíkó"},{"id":"Moldóvía","name":"Moldóvía"},{"id":"Mósambik","name":"Mósambik"},{"id":"Mön","name":"Mön"},{"id":"Namibía","name":"Namibía"},{"id":"Níkaragúa","name":"Níkaragúa"},{"id":"Norður-Írland","name":"Norður-Írland"},{"id":"Norður-Marinaeyjar","name":"Norður-Marinaeyjar"},{"id":"Noregur","name":"Noregur"},{"id":"Nýja-Kaledónía","name":"Nýja-Kaledónía"},{"id":"Nýja-Sjáland","name":"Nýja-Sjáland"},{"id":"Óman","name":"Óman"},{"id":"Pakistan","name":"Pakistan"},{"id":"Panama","name":"Panama"},{"id":"Paragvæ","name":"Paragvæ"},{"id":"Perú","name":"Perú"},{"id":"Portúgal","name":"Portúgal"},{"id":"Portúgal - Asóraeyjar","name":"Portúgal - Asóraeyjar"},{"id":"Portúgal - Madeira","name":"Portúgal - Madeira"},{"id":"Pólland","name":"Pólland"},{"id":"Púertó Ríkó","name":"Púertó Ríkó"},{"id":"Reunion Island","name":"Reunion Island"},{"id":"Roatan Island - Hondúras","name":"Roatan Island - Hondúras"},{"id":"Rúmenía","name":"Rúmenía"},{"id":"Rússland","name":"Rússland"},{"id":"Saipan","name":"Saipan"},{"id":"Sambía","name":"Sambía"},{"id":"Sameinuðu arabísku furstadæmin","name":"Sameinuðu arabísku furstadæmin"},{"id":"Sádi-Arabía","name":"Sádi-Arabía"},{"id":"Serbía","name":"Serbía"},{"id":"Simbabwe","name":"Simbabwe"},{"id":"Singapúr","name":"Singapúr"},{"id":"Síle (Chile)","name":"Síle (Chile)"},{"id":"Slóvakía","name":"Slóvakía"},{"id":"Slóvenía","name":"Slóvenía"},{"id":"Spánn - Baleariceyjar","name":"Spánn - Baleariceyjar"},{"id":"Spánn - Kanaríeyjar","name":"Spánn - Kanaríeyjar"},{"id":"Spánn - meginlandið","name":"Spánn - meginlandið"},{"id":"Sri Lanka","name":"Sri Lanka"},{"id":"St. Barthelemy","name":"St. Barthelemy"},{"id":"St. Croix","name":"St. Croix"},{"id":"St. Kitts","name":"St. Kitts"},{"id":"St. Lúsía","name":"St. Lúsía"},{"id":"St. Martin","name":"St. Martin"},{"id":"St. Martin","name":"St. Martin"},{"id":"St. Tómas","name":"St. Tómas"},{"id":"Suður-Afríka","name":"Suður-Afríka"},{"id":"Suður-Kórea","name":"Suður-Kórea"},{"id":"Súrinam","name":"Súrinam"},{"id":"Svartfjallaland","name":"Svartfjallaland"},{"id":"Sviss","name":"Sviss"},{"id":"Svíþjóð","name":"Svíþjóð"},{"id":"Swasíland","name":"Swasíland"},{"id":"Tahíti","name":"Tahíti"},{"id":"Taiwan","name":"Taiwan"},{"id":"Tansanía","name":"Tansanía"},{"id":"Tékkland","name":"Tékkland"},{"id":"Tortola","name":"Tortola"},{"id":"Trínidad","name":"Trínidad"},{"id":"Turks and Caicos Islands","name":"Turks and Caicos Islands"},{"id":"Túnis","name":"Túnis"},{"id":"Tyrkland","name":"Tyrkland"},{"id":"Tyrkneska lýðveldið á Norður-Kýpur","name":"Tyrkneska lýðveldið á Norður-Kýpur"},{"id":"Tæland","name":"Tæland"},{"id":"Ungverjaland","name":"Ungverjaland"},{"id":"Úkraína","name":"Úkraína"},{"id":"Úrugvæ","name":"Úrugvæ"},{"id":"Vanuatu","name":"Vanuatu"},{"id":"Venesúela","name":"Venesúela"},{"id":"Þýskaland","name":"Þýskaland"}]